dictionary/__init__.py
dictionary/dictionary.py
ogi_cet_cs453_hw1-2.0.1.dist-info/METADATA
ogi_cet_cs453_hw1-2.0.1.dist-info/WHEEL
ogi_cet_cs453_hw1-2.0.1.dist-info/top_level.txt
ogi_cet_cs453_hw1-2.0.1.dist-info/RECORD
