Metadata-Version: 2.1
Name: ogi-cet-cs453-hw1
Version: 2.0.1
Summary: UNKNOWN
Author: Oğulcan Çetinkaya
License: UNKNOWN
Platform: UNKNOWN
Requires-Python: >=3.8
Requires-Dist: requests (>=2.23.0)
